scheduler/__init__.py
scheduler/error.py
scheduler/message.py
scheduler/prioritization.py
scheduler/py.typed
scheduler/util.py
scheduler/asyncio/__init__.py
scheduler/asyncio/job.py
scheduler/asyncio/scheduler.py
scheduler/base/__init__.py
scheduler/base/definition.py
scheduler/base/job.py
scheduler/base/job_timer.py
scheduler/base/job_util.py
scheduler/base/scheduler.py
scheduler/base/scheduler_util.py
scheduler/base/timingtype.py
scheduler/threading/__init__.py
scheduler/threading/job.py
scheduler/threading/scheduler.py
scheduler/trigger/__init__.py
scheduler/trigger/core.py
scheduler-0.8.7.dist-info/LICENSE
scheduler-0.8.7.dist-info/METADATA
scheduler-0.8.7.dist-info/WHEEL
scheduler-0.8.7.dist-info/top_level.txt
scheduler-0.8.7.dist-info/RECORD
