Metadata-Version: 2.1
Name: scheduler
Version: 0.8.7
Summary: A simple in-process python scheduler library with asyncio, threading and timezone support.
Author-email: "Fabian A. Preiss" <fpreiss@digon.io>, "Jendrik A. Potyka" <jpotyka@digon.io>
Maintainer-email: "Fabian A. Preiss" <fpreiss@digon.io>, "Jendrik A. Potyka" <jpotyka@digon.io>
License: LGPLv3
Project-URL: Repository, https://gitlab.com/DigonIO/scheduler
Project-URL: Documentation, https://digon.io/hyd/project/scheduler/t/master
Project-URL: Changelog, https://gitlab.com/DigonIO/scheduler/-/blob/master/CHANGELOG.md
Project-URL: Bug Tracker, https://gitlab.com/DigonIO/scheduler/-/issues
Keywords: scheduler,schedule,asyncio,threading,datetime,date,time,timedelta,timezone,timing
Classifier: Development Status :: 4 - Beta
Classifier: Intended Audience :: Developers
Classifier: License :: OSI Approved :: GNU Lesser General Public License v3 (LGPLv3)
Classifier: Programming Language :: Python :: 3.9
Classifier: Programming Language :: Python :: 3.10
Classifier: Programming Language :: Python :: 3.11
Classifier: Programming Language :: Python :: 3.12
Classifier: Programming Language :: Python :: Implementation :: CPython
Classifier: Topic :: Scientific/Engineering
Classifier: Topic :: Software Development :: Libraries
Classifier: Operating System :: OS Independent
Classifier: Typing :: Typed
Requires-Python: >=3.9
License-File: LICENSE
Requires-Dist: typeguard>=3.0.0
